getpass.py
setup.py
micropython_getpass.egg-info/PKG-INFO
micropython_getpass.egg-info/SOURCES.txt
micropython_getpass.egg-info/dependency_links.txt
micropython_getpass.egg-info/top_level.txt